obfuscation_detection/__init__.py
obfuscation_detection/main.py
obfuscation_detection/model.py
obfuscation_detection/models/od-cmdexe-xgb-model.json
obfuscation_detection-1.0.0.dist-info/licenses/LICENSE
obfuscation_detection-1.0.0.dist-info/METADATA
obfuscation_detection-1.0.0.dist-info/WHEEL
obfuscation_detection-1.0.0.dist-info/top_level.txt
obfuscation_detection-1.0.0.dist-info/RECORD
