Metadata-Version: 2.4
Name: obfuscation-detection
Version: 1.0.0
Summary: Python module for obfuscation classification in command line executions
Home-page: https://github.com/adobe/obfuscation-detection
Author: Wilson Tang
Author-email: wilson.tang06@gmail.com
Project-URL: Bug Tracker, https://github.com/adobe/obfuscation-detection/issues
Classifier: Programming Language :: Python :: 3.0
Classifier: License :: OSI Approved :: Apache Software License
Classifier: Operating System :: OS Independent
Requires-Python: >=3.10
License-File: LICENSE
Requires-Dist: xgboost
Requires-Dist: scikit-learn
Requires-Dist: numpy
Dynamic: author
Dynamic: author-email
Dynamic: classifier
Dynamic: description
Dynamic: description-content-type
Dynamic: home-page
Dynamic: license-file
Dynamic: project-url
Dynamic: requires-dist
Dynamic: requires-python
Dynamic: summary
